PTJPL/ECOv002-cal-val-PT-JPL-inputs.csv
PTJPL/ECOv002-cal-val-PT-JPL-outputs.csv
PTJPL/ECOv002-static-tower-PT-JPL-inputs.csv
PTJPL/ECOv002_calval_PTJPL_inputs.py
PTJPL/ECOv002_static_tower_PTJPL_inputs.py
PTJPL/PTJPL.py
PTJPL/Topt.py
PTJPL/Topt_mean_CMG_int16.tif
PTJPL/__init__.py
PTJPL/constants.py
PTJPL/fAPARmax.py
PTJPL/fAPARmax_mean_CMG_int16.tif
PTJPL/generate_PTJPL_input_dataset.py
PTJPL/generate_PTJPL_inputs.py
PTJPL/generate_static_PTJPL_input_dataset.py
PTJPL/model.py
PTJPL/process_PTJPL_table.py
PTJPL/verify.py
PTJPL/version.py
PTJPL/partitioning/__init__.py
PTJPL/partitioning/canopy_latent_heat_flux.py
PTJPL/partitioning/fM.py
PTJPL/partitioning/fSM.py
PTJPL/partitioning/fT.py
PTJPL/partitioning/fg.py
PTJPL/partitioning/fwet.py
PTJPL/partitioning/interception.py
PTJPL/partitioning/partitioning.py
PTJPL/partitioning/soil_latent_heat_flux.py
PTJPL/partitioning/soil_net_radiation.py
PTJPL/vegetation_conversion/SAVI_from_NDVI.py
PTJPL/vegetation_conversion/__init__.py
PTJPL/vegetation_conversion/fAPAR_from_SAVI.py
PTJPL/vegetation_conversion/fIPAR_from_NDVI.py
PTJPL/vegetation_conversion/vegetation_conversion.py
ptjpl-1.8.1.dist-info/licenses/LICENSE
ptjpl-1.8.1.dist-info/METADATA
ptjpl-1.8.1.dist-info/WHEEL
ptjpl-1.8.1.dist-info/top_level.txt
ptjpl-1.8.1.dist-info/RECORD
