Metadata-Version: 2.4
Name: PTJPL
Version: 1.8.1
Summary: Priestley-Taylor Jet Propulsion Laboratory Evapotranspiration Model
Author-email: Gregory Halverson <gregory.h.halverson@jpl.nasa.gov>, "Joshua B. Fisher" <jbfisher@chapman.edu>, "Claire S. Villanueva-Weeks" <claire.s.villanueva-weeks@jpl.gov>
Project-URL: Homepage, https://github.com/JPL-Evapotranspiration-Algorithms/PTJPL
Classifier: Programming Language :: Python :: 3
Classifier: Operating System :: OS Independent
Requires-Python: >=3.10
License-File: LICENSE
Requires-Dist: carlson-leaf-area-index
Requires-Dist: colored-logging
Requires-Dist: daylight-evapotranspiration>=1.2.1
Requires-Dist: GEOS5FP>=1.2.2
Requires-Dist: meteorology-conversion
Requires-Dist: numpy
Requires-Dist: pandas
Requires-Dist: priestley-taylor>=1.1.3
Requires-Dist: rasters>=1.7.1
Requires-Dist: SEBAL-soil-heat-flux
Requires-Dist: solar-apparent-time
Requires-Dist: verma-net-radiation>=1.8.0
Provides-Extra: dev
Requires-Dist: build; extra == "dev"
Requires-Dist: pytest>=6.0; extra == "dev"
Requires-Dist: pytest-cov; extra == "dev"
Requires-Dist: jupyter; extra == "dev"
Requires-Dist: pytest; extra == "dev"
Requires-Dist: twine; extra == "dev"
Dynamic: license-file
